pygments_rspec
