Metadata-Version: 1.0
Name: pygments-rspec
Version: 0.2
Summary: Pygments lexer for Ruby + RSpec.
Home-page: https://github.com/hugomaiavieira/pygments-rspec
Author: Hugo Maia Vieira
Author-email: hugomaiavieira@gmail.com
License: BSD
Keywords: pygments ruby rspec lexer
Platform: UNKNOWN
Classifier: Development Status :: 4 - Beta
Classifier: Environment :: Plugins
Classifier: Intended Audience :: Developers
Classifier: License :: OSI Approved :: BSD License
Classifier: Operating System :: OS Independent
Classifier: Programming Language :: Python
Classifier: Programming Language :: Python :: 2
Classifier: Programming Language :: Python :: 3
Classifier: Topic :: Software Development :: Libraries :: Python Modules
